datablade/__init__.py
datablade/blade.py
datablade/core/__init__.py
datablade/core/frames.py
datablade/core/json.py
datablade/core/lists.py
datablade/core/messages.py
datablade/core/strings.py
datablade/core/zip.py
datablade/dataframes/__init__.py
datablade/dataframes/frames.py
datablade/dataframes/readers.py
datablade/io/__init__.py
datablade/io/json.py
datablade/io/zip.py
datablade/sql/__init__.py
datablade/sql/bulk_load.py
datablade/sql/ddl.py
datablade/sql/ddl_pyarrow.py
datablade/sql/dialects.py
datablade/sql/quoting.py
datablade/utils/__init__.py
datablade/utils/lists.py
datablade/utils/logging.py
datablade/utils/messages.py
datablade/utils/strings.py
datablade-0.0.5.dist-info/licenses/LICENSE
datablade-0.0.5.dist-info/METADATA
datablade-0.0.5.dist-info/WHEEL
datablade-0.0.5.dist-info/top_level.txt
datablade-0.0.5.dist-info/RECORD
