Metadata-Version: 2.4
Name: datablade
Version: 0.0.5
Summary: datablade is a suite of functions to provide standard syntax across data engineering projects.
Author-email: Brent Carpenetti <brentwc.git@pm.me>
License: MIT License
Requires-Python: >=3.12
License-File: LICENSE
Requires-Dist: pandas
Requires-Dist: pyarrow
Requires-Dist: numpy
Requires-Dist: openpyxl
Requires-Dist: requests
Provides-Extra: performance
Requires-Dist: polars; extra == "performance"
Requires-Dist: psutil; extra == "performance"
Provides-Extra: test
Requires-Dist: pytest>=7.0.0; extra == "test"
Requires-Dist: pytest-cov>=4.0.0; extra == "test"
Requires-Dist: pytest-mock>=3.10.0; extra == "test"
Provides-Extra: dev
Requires-Dist: pytest>=7.0.0; extra == "dev"
Requires-Dist: pytest-cov>=4.0.0; extra == "dev"
Requires-Dist: pytest-mock>=3.10.0; extra == "dev"
Requires-Dist: polars; extra == "dev"
Requires-Dist: psutil; extra == "dev"
Requires-Dist: black; extra == "dev"
Requires-Dist: flake8; extra == "dev"
Requires-Dist: mypy; extra == "dev"
Requires-Dist: isort; extra == "dev"
Provides-Extra: all
Requires-Dist: polars; extra == "all"
Requires-Dist: psutil; extra == "all"
Requires-Dist: pytest>=7.0.0; extra == "all"
Requires-Dist: pytest-cov>=4.0.0; extra == "all"
Requires-Dist: pytest-mock>=3.10.0; extra == "all"
Requires-Dist: black; extra == "all"
Requires-Dist: flake8; extra == "all"
Requires-Dist: mypy; extra == "all"
Requires-Dist: isort; extra == "all"
Dynamic: license-file
